Metadata-Version: 1.0
Name: printbig
Version: 0.6.2.2
Summary: An python package that prints bigger than anyone. It prints HUGE
Home-page: https://github.com/AlexAndrei98/testpackage
Author: Alex Andrei
Author-email: alexandrei1998@hotmail.it
License: MIT
Platform: UNKNOWN
